colabtestingpkg/__init__.py
colabtestingpkg/alphafold.py
colabtestingpkg/authorize.py
colabtestingpkg/watch.py
colabtestingpkg-0.1.6.dist-info/WHEEL
colabtestingpkg-0.1.6.dist-info/METADATA
colabtestingpkg-0.1.6.dist-info/RECORD
