Metadata-Version: 2.1
Name: colabtestingpkg
Version: 0.1.6
Summary: 
Author: Your Name
Author-email: you@example.com
Requires-Python: >=3.7,<4.0
Classifier: Programming Language :: Python :: 3
Classifier: Programming Language :: Python :: 3.10
Classifier: Programming Language :: Python :: 3.7
Classifier: Programming Language :: Python :: 3.8
Classifier: Programming Language :: Python :: 3.9
Requires-Dist: biopython (>=1.70,<2.0)
Requires-Dist: google-api-python-client (>=2.42.0,<3.0.0)
Requires-Dist: google-auth (>=2.6,<3.0)
Requires-Dist: google-cloud-firestore (>=2.4.0,<3.0.0)
Requires-Dist: google-cloud-storage (>=2.2.1,<3.0.0)
Requires-Dist: tqdm (>=4.64.0,<5.0.0)
